spade_llm/__init__.py
spade_llm/__main__.py
spade_llm/version.py
spade_llm/agent/__init__.py
spade_llm/agent/chat_agent.py
spade_llm/agent/coordinator_agent.py
spade_llm/agent/llm_agent.py
spade_llm/behaviour/__init__.py
spade_llm/behaviour/human_interaction.py
spade_llm/behaviour/llm_behaviour.py
spade_llm/context/__init__.py
spade_llm/context/_types.py
spade_llm/context/context_manager.py
spade_llm/context/management.py
spade_llm/guardrails/__init__.py
spade_llm/guardrails/base.py
spade_llm/guardrails/implementations.py
spade_llm/guardrails/processor.py
spade_llm/guardrails/types.py
spade_llm/human_interface/__init__.py
spade_llm/human_interface/start_server.py
spade_llm/human_interface/web_server.py
spade_llm/mcp/__init__.py
spade_llm/mcp/config.py
spade_llm/mcp/factory.py
spade_llm/mcp/session.py
spade_llm/mcp/adapters/__init__.py
spade_llm/mcp/adapters/base.py
spade_llm/mcp/adapters/sse.py
spade_llm/mcp/adapters/stdio.py
spade_llm/mcp/adapters/streamable_http.py
spade_llm/memory/__init__.py
spade_llm/memory/agent_base_memory.py
spade_llm/memory/agent_base_memory_tools.py
spade_llm/memory/interaction_memory.py
spade_llm/memory/backends/__init__.py
spade_llm/memory/backends/base.py
spade_llm/memory/backends/sqlite.py
spade_llm/providers/__init__.py
spade_llm/providers/base_provider.py
spade_llm/providers/llm_provider.py
spade_llm/routing/__init__.py
spade_llm/routing/decorators.py
spade_llm/routing/types.py
spade_llm/tools/__init__.py
spade_llm/tools/human_in_the_loop.py
spade_llm/tools/langchain_adapter.py
spade_llm/tools/llm_tool.py
spade_llm/utils/__init__.py
spade_llm/utils/env_loader.py
spade_llm-0.2.0.dist-info/licenses/LICENSE
spade_llm-0.2.0.dist-info/METADATA
spade_llm-0.2.0.dist-info/WHEEL
spade_llm-0.2.0.dist-info/entry_points.txt
spade_llm-0.2.0.dist-info/top_level.txt
spade_llm-0.2.0.dist-info/RECORD
