Metadata-Version: 2.4
Name: spade_llm
Version: 0.2.0
Summary: Extension for SPADE to integrate Large Language Models in agents
Home-page: https://github.com/sosanzma/spade_llm
Author: Manel Soler Sanz
Author-email: masosan9@upvnet.upv.es
Project-URL: Bug Reports, https://github.com/sosanzma/spade_llm/issues
Project-URL: Source, https://github.com/sosanzma/spade_llm
Project-URL: Documentation, https://sosanzma.github.io/spade_llm
Keywords: spade llm ai agents multi-agent-systems openai ollama
Classifier: Development Status :: 4 - Beta
Classifier: Intended Audience :: Developers
Classifier: License :: OSI Approved :: MIT License
Classifier: Programming Language :: Python :: 3.10
Classifier: Programming Language :: Python :: 3.11
Classifier: Programming Language :: Python :: 3.12
Classifier: Topic :: Software Development :: Libraries :: Python Modules
Classifier: Topic :: Scientific/Engineering :: Artificial Intelligence
Classifier: Topic :: Internet :: XMPP
Classifier: Operating System :: OS Independent
Requires-Python: >=3.10
License-File: LICENSE
Requires-Dist: spade>=4.0.0
Requires-Dist: openai>=1.0.0
Requires-Dist: pydantic>=2.0.0
Requires-Dist: aiohttp>=3.8.0
Requires-Dist: python-dateutil>=2.8.2
Requires-Dist: mcp>=1.8.0
Requires-Dist: aiosqlite>=0.17.0
Provides-Extra: langchain
Requires-Dist: langchain_community>=0.3.2; extra == "langchain"
Provides-Extra: dev
Requires-Dist: pytest>=7.0.0; extra == "dev"
Requires-Dist: pytest-asyncio>=0.21.0; extra == "dev"
Requires-Dist: pytest-cov>=4.0.0; extra == "dev"
Requires-Dist: pytest-mock>=3.10.0; extra == "dev"
Requires-Dist: flake8>=6.0.0; extra == "dev"
Requires-Dist: black>=23.0.0; extra == "dev"
Requires-Dist: isort>=5.12.0; extra == "dev"
Requires-Dist: coverage>=7.0.0; extra == "dev"
Requires-Dist: tox>=4.0.0; extra == "dev"
Requires-Dist: pre-commit>=3.0.0; extra == "dev"
Provides-Extra: docs
Requires-Dist: sphinx>=6.0.0; extra == "docs"
Requires-Dist: sphinx-rtd-theme>=1.2.0; extra == "docs"
Provides-Extra: all
Requires-Dist: langchain_community>=0.3.2; extra == "all"
Requires-Dist: google-generativeai>=0.3.0; extra == "all"
Requires-Dist: anthropic>=0.5.0; extra == "all"
Dynamic: author
Dynamic: author-email
Dynamic: classifier
Dynamic: description
Dynamic: description-content-type
Dynamic: home-page
Dynamic: keywords
Dynamic: license-file
Dynamic: project-url
Dynamic: provides-extra
Dynamic: requires-dist
Dynamic: requires-python
Dynamic: summary
